{
  "lastUpdated": "2025-11-26 00:51:43 JST",
  "profiles": [
    {
      "id": "001",
      "registeredDate": "2025-11-26",
      "updatedDate": "2025-11-26",
      "avatarName": "桔梗",
      "avatarNameUrl": "https://booth.pm/ja/items/3681787",
      "profileVersion": "1.0",
      "avatarAuthor": "ポンデロニウム研究所",
      "avatarAuthorUrl": "https://ponderogen.booth.pm/",
      "profileAuthor": "Nine Gates",
      "profileAuthorUrl": "https://yamirin.booth.pm/",
      "official": true,
      "downloadMethod": "Booth",
      "downloadLocation": "https://booth.pm/ja/items/7657840",
      "imageUrl": "https://booth.pximg.net/ed52788c-0b3b-4e38-9ded-1e5797daf0ef/i/3681787/2409bb9f-24f3-42dd-8ad6-89a0656f2166_base_resized.jpg",
      "pricing": "もちふぃった～同梱",
      "price": "2500",
      "forwardSupport": true,
      "reverseSupport": true
    },
    {
      "id": "002",
      "registeredDate": "2025-11-26",
      "updatedDate": "2025-11-26",
      "avatarName": "ベリル",
      "avatarNameUrl": "https://yamirin.booth.pm/items/4930259",
      "profileVersion": "1.0",
      "avatarAuthor": "Nine Gates",
      "avatarAuthorUrl": "https://yamirin.booth.pm/",
      "profileAuthor": "Nine Gates",
      "profileAuthorUrl": "https://yamirin.booth.pm/",
      "official": true,
      "downloadMethod": "Booth",
      "downloadLocation": "https://booth.pm/ja/items/7657840",
      "imageUrl": "https://booth.pximg.net/11d082f4-13bc-482b-b48f-07e27703a8aa/i/4930259/74113ccb-a6f7-45e3-9df6-13db9ff9e916_base_resized.jpg",
      "pricing": "アバター同梱、もちふぃった～同梱",
      "price": "5500円,2500",
      "forwardSupport": true,
      "reverseSupport": true
    },
    {
      "id": "003",
      "registeredDate": "2025-11-26",
      "updatedDate": "2025-11-26",
      "avatarName": "マヌカ",
      "avatarNameUrl": "https://booth.pm/ja/items/5058077",
      "profileVersion": "2.0.0",
      "avatarAuthor": "JINGO CHANNEL",
      "avatarAuthorUrl": "https://jingo1016.booth.pm/",
      "profileAuthor": "Nine Gates",
      "profileAuthorUrl": "https://yamirin.booth.pm/",
      "official": true,
      "downloadMethod": "Booth",
      "downloadLocation": "https://booth.pm/ja/items/7657840",
      "imageUrl": "https://booth.pximg.net/8a7426aa-ba62-4ef0-9e7d-2c8ea96e7c9b/i/5058077/a18424fe-a56e-411a-9c47-27c56909593c_base_resized.jpg",
      "pricing": "もちふぃった～同梱",
      "price": "2500",
      "forwardSupport": true,
      "reverseSupport": true
    },
    {
      "id": "004",
      "registeredDate": "2025-11-26",
      "updatedDate": "2025-11-26",
      "avatarName": "Ciel - シエル -",
      "avatarNameUrl": "https://armoirelepus.booth.pm/items/3368697",
      "profileVersion": "1.0",
      "avatarAuthor": "れぴのちゃん",
      "avatarAuthorUrl": "https://armoirelepus.booth.pm/",
      "profileAuthor": "れぴのちゃん",
      "profileAuthorUrl": "https://armoirelepus.booth.pm/",
      "official": true,
      "downloadMethod": "Booth",
      "downloadLocation": "https://armoirelepus.booth.pm/items/7687000",
      "imageUrl": "https://booth.pximg.net/d398d5cc-41ab-4a3a-b7fe-eec9a3d94a3b/i/7687000/7b28b186-134a-4413-9046-24e0cdea89c1_base_resized.jpg",
      "pricing": "無料",
      "price": "",
      "forwardSupport": true,
      "reverseSupport": false
    },
    {
      "id": "005",
      "registeredDate": "2025-11-26",
      "updatedDate": "2025-11-26",
      "avatarName": "森羅",
      "avatarNameUrl": "https://booth.pm/ja/items/4707634",
      "profileVersion": "1.0",
      "avatarAuthor": "mio3io",
      "avatarAuthorUrl": "https://mio3io.booth.pm/",
      "profileAuthor": "kuromaru9",
      "profileAuthorUrl": "https://kuromaru9.booth.pm/",
      "official": false,
      "downloadMethod": "Booth",
      "downloadLocation": "https://kuromaru9.booth.pm/items/7613516",
      "imageUrl": "https://booth.pximg.net/40e6fb67-d32a-48f9-9820-e064ff7b8670/i/7613516/242fd891-5677-487a-b2bc-da2776454829_base_resized.jpg",
      "pricing": "無料",
      "price": "",
      "forwardSupport": true,
      "reverseSupport": true
    },
    {
      "id": "006",
      "registeredDate": "2025-11-26",
      "updatedDate": "2025-11-26",
      "avatarName": "Lapwing",
      "avatarNameUrl": "https://kujishift.booth.pm/items/4993931",
      "profileVersion": "1.0",
      "avatarAuthor": "kuji",
      "avatarAuthorUrl": "https://kujishift.booth.pm/",
      "profileAuthor": "kuromaru9",
      "profileAuthorUrl": "https://kuromaru9.booth.pm/",
      "official": false,
      "downloadMethod": "Booth",
      "downloadLocation": "https://kuromaru9.booth.pm/items/7613516",
      "imageUrl": "https://booth.pximg.net/40e6fb67-d32a-48f9-9820-e064ff7b8670/i/7613516/735e0019-ac20-4162-b30f-32eaf977f4ae_base_resized.jpg",
      "pricing": "無料",
      "price": "",
      "forwardSupport": true,
      "reverseSupport": true
    },
    {
      "id": "007",
      "registeredDate": "2025-11-26",
      "updatedDate": "2025-11-26",
      "avatarName": "ルキフェル -Lucifer-",
      "avatarNameUrl": "https://nyahuuu.booth.pm/items/4358123",
      "profileVersion": "1.0",
      "avatarAuthor": "香坂もち",
      "avatarAuthorUrl": "https://nyahuuu.booth.pm/",
      "profileAuthor": "kuromaru9",
      "profileAuthorUrl": "https://kuromaru9.booth.pm/",
      "official": false,
      "downloadMethod": "Booth",
      "downloadLocation": "https://kuromaru9.booth.pm/items/7552195",
      "imageUrl": "https://booth.pximg.net/a8591f3a-a029-42e5-a769-a738c143f354/i/4358123/eaeff390-b9aa-4a14-8d9c-5c105fe9da42_base_resized.jpg",
      "pricing": "無料",
      "price": "",
      "forwardSupport": true,
      "reverseSupport": true
    },
    {
      "id": "008",
      "registeredDate": "2025-11-26",
      "updatedDate": "2025-11-26",
      "avatarName": "イェーナ -Yena-",
      "avatarNameUrl": "https://stray-lamb.booth.pm/items/4398963",
      "profileVersion": "1.0",
      "avatarAuthor": "火村ユウヤ",
      "avatarAuthorUrl": "https://stray-lamb.booth.pm/",
      "profileAuthor": "kuromaru9",
      "profileAuthorUrl": "https://kuromaru9.booth.pm/",
      "official": false,
      "downloadMethod": "Booth",
      "downloadLocation": "https://kuromaru9.booth.pm/items/7552195",
      "imageUrl": "https://booth.pximg.net/c5f5c24d-2662-43bc-98be-454d8623bccb/i/4398963/a8503d79-e694-4316-9a83-572059dbbe62_base_resized.jpg",
      "pricing": "無料",
      "price": "",
      "forwardSupport": true,
      "reverseSupport": true
    },
    {
      "id": "009",
      "registeredDate": "2025-11-26",
      "updatedDate": "2025-11-26",
      "avatarName": "リセ -Lise-",
      "avatarNameUrl": "https://regs.booth.pm/items/4390073",
      "profileVersion": "1.0",
      "avatarAuthor": "れじ",
      "avatarAuthorUrl": "https://regs.booth.pm/",
      "profileAuthor": "kuromaru9\n",
      "profileAuthorUrl": "https://kuromaru9.booth.pm/",
      "official": false,
      "downloadMethod": "Booth",
      "downloadLocation": "https://kuromaru9.booth.pm/items/7552195",
      "imageUrl": "https://booth.pximg.net/38d12e48-b117-4086-a5c7-b02cd8f9c952/i/4390073/0bb0d1dd-4f64-4493-bf17-31abbfd113e9_base_resized.jpg",
      "pricing": "無料",
      "price": "",
      "forwardSupport": true,
      "reverseSupport": true
    },
    {
      "id": "010",
      "registeredDate": "2025-11-26",
      "updatedDate": "2025-11-26",
      "avatarName": "ネミア -Nenmir-",
      "avatarNameUrl": "https://rokota.booth.pm/items/4376366",
      "profileVersion": "1.0",
      "avatarAuthor": "roko shop",
      "avatarAuthorUrl": "https://rokota.booth.pm/",
      "profileAuthor": "kuromaru9",
      "profileAuthorUrl": "https://kuromaru9.booth.pm/",
      "official": false,
      "downloadMethod": "Booth",
      "downloadLocation": "https://kuromaru9.booth.pm/items/7552195",
      "imageUrl": "https://booth.pximg.net/e3843aaf-9232-4a4c-9d6e-e0a09646f417/i/4376366/566a769d-c448-446a-aaae-b337195968ef_base_resized.jpg",
      "pricing": "無料",
      "price": "",
      "forwardSupport": true,
      "reverseSupport": true
    },
    {
      "id": "011",
      "registeredDate": "2025-11-26",
      "updatedDate": "2025-11-26",
      "avatarName": "むんき -Munkki -",
      "avatarNameUrl": "https://nanka-tsukurouyo.booth.pm/items/5787485",
      "profileVersion": "1.0",
      "avatarAuthor": "thw",
      "avatarAuthorUrl": "https://nanka-tsukurouyo.booth.pm/",
      "profileAuthor": "kuromaru9",
      "profileAuthorUrl": "https://kuromaru9.booth.pm/",
      "official": false,
      "downloadMethod": "Booth",
      "downloadLocation": "https://kuromaru9.booth.pm/items/7552195",
      "imageUrl": "https://booth.pximg.net/4720f57f-29f2-4c9f-af38-5b7b81653a21/i/5787485/661465ae-2443-4702-8919-d1528e1801f8_base_resized.jpg",
      "pricing": "無料",
      "price": "",
      "forwardSupport": true,
      "reverseSupport": true
    },
    {
      "id": "012",
      "registeredDate": "2025-11-26",
      "updatedDate": "2025-11-26",
      "avatarName": "かんぺきメイドメロトロン",
      "avatarNameUrl": "https://kuromaru9.booth.pm/items/5860593",
      "profileVersion": "1.0",
      "avatarAuthor": "kuromaru9",
      "avatarAuthorUrl": "https://kuromaru9.booth.pm/",
      "profileAuthor": "kuromaru9",
      "profileAuthorUrl": "https://kuromaru9.booth.pm/",
      "official": true,
      "downloadMethod": "Booth",
      "downloadLocation": "https://kuromaru9.booth.pm/items/7552195",
      "imageUrl": "https://booth.pximg.net/40e6fb67-d32a-48f9-9820-e064ff7b8670/i/5860593/3ca1d94b-a816-4cc4-83f8-beea243f799c_base_resized.jpg",
      "pricing": "無料",
      "price": "",
      "forwardSupport": true,
      "reverseSupport": true
    },
    {
      "id": "013",
      "registeredDate": "2025-11-26",
      "updatedDate": "2025-11-26",
      "avatarName": "びしょぬれのしずくさん",
      "avatarNameUrl": "https://kuromaru9.booth.pm/items/3828632",
      "profileVersion": "1.0",
      "avatarAuthor": "kuromaru9",
      "avatarAuthorUrl": "https://kuromaru9.booth.pm/",
      "profileAuthor": "kuromaru9",
      "profileAuthorUrl": "https://kuromaru9.booth.pm/",
      "official": true,
      "downloadMethod": "Booth",
      "downloadLocation": "https://kuromaru9.booth.pm/items/3828632",
      "imageUrl": "https://booth.pximg.net/40e6fb67-d32a-48f9-9820-e064ff7b8670/i/3828632/77568536-fcea-4ea0-b94f-c6ea29529174_base_resized.jpg",
      "pricing": "無料",
      "price": "",
      "forwardSupport": true,
      "reverseSupport": true
    },
    {
      "id": "014",
      "registeredDate": "2025-11-26",
      "updatedDate": "2025-11-26",
      "avatarName": "バナナのばななちゃん",
      "avatarNameUrl": "https://kuromaru9.booth.pm/items/2411814",
      "profileVersion": "1.0",
      "avatarAuthor": "kuromaru9",
      "avatarAuthorUrl": "https://kuromaru9.booth.pm/",
      "profileAuthor": "kuromaru9",
      "profileAuthorUrl": "https://kuromaru9.booth.pm/",
      "official": true,
      "downloadMethod": "Booth",
      "downloadLocation": "https://kuromaru9.booth.pm/items/2411814",
      "imageUrl": "https://booth.pximg.net/40e6fb67-d32a-48f9-9820-e064ff7b8670/i/2411814/3ec05bbf-456b-43c2-8029-8c2b6f24c975_base_resized.jpg",
      "pricing": "無料",
      "price": "",
      "forwardSupport": true,
      "reverseSupport": true
    },
    {
      "id": "015",
      "registeredDate": "2025-11-26",
      "updatedDate": "2025-11-26",
      "avatarName": "ナナセ・ノワール -Nanase Noir-",
      "avatarNameUrl": "https://booth.pm/ja/items/5827815",
      "profileVersion": "1.0",
      "avatarAuthor": "ステラー",
      "avatarAuthorUrl": "https://steller.booth.pm/",
      "profileAuthor": "ステラー",
      "profileAuthorUrl": "https://steller.booth.pm/",
      "official": true,
      "downloadMethod": "Booth",
      "downloadLocation": "https://booth.pm/ja/items/5827815",
      "imageUrl": "https://booth.pximg.net/8dd1ea6b-1c31-4d82-bfec-cbc05177d146/i/5827815/cc5a9581-ecc5-4a30-9596-ac144de3d1f5_base_resized.jpg",
      "pricing": "無料",
      "price": "",
      "forwardSupport": true,
      "reverseSupport": true
    },
    {
      "id": "016",
      "registeredDate": "2025-11-26",
      "updatedDate": "2025-11-26",
      "avatarName": "マリシア - Marycia -",
      "avatarNameUrl": "https://booth.pm/ja/items/6305948",
      "profileVersion": "1.0",
      "avatarAuthor": "BeroarN",
      "avatarAuthorUrl": "https://brn.booth.pm/",
      "profileAuthor": "BeroarN",
      "profileAuthorUrl": "https://brn.booth.pm/",
      "official": true,
      "downloadMethod": "Booth",
      "downloadLocation": "https://booth.pm/ja/items/6305948",
      "imageUrl": "https://booth.pximg.net/f6d23951-d61e-4e47-908b-521afbb47fbf/i/6305948/40e8f0b2-82a8-49c2-a332-eebe2441968f_base_resized.jpg",
      "pricing": "アバター同梱",
      "price": "",
      "forwardSupport": true,
      "reverseSupport": false
    },
    {
      "id": "017",
      "registeredDate": "2025-11-26",
      "updatedDate": "2025-11-26",
      "avatarName": "サフィー-Sapphy-",
      "avatarNameUrl": "https://booth.pm/ja/items/3939858",
      "profileVersion": "1.0",
      "avatarAuthor": "yueou",
      "avatarAuthorUrl": "https://yueou.booth.pm/",
      "profileAuthor": "yueou",
      "profileAuthorUrl": "https://yueou.booth.pm/",
      "official": true,
      "downloadMethod": "Booth",
      "downloadLocation": "https://booth.pm/ja/items/3939858",
      "imageUrl": "https://booth.pximg.net/8e4c6e25-746f-4ea7-b9a8-51d10ed80b3b/i/3939858/f80a2721-ccbd-465f-991a-8bfa2bb7fff8_base_resized.jpg",
      "pricing": "無料",
      "price": "",
      "forwardSupport": true,
      "reverseSupport": true
    }
  ]
}